vscode_essentials/__init__.py
vscode_essentials/__pycache__/__init__.cpython-311.pyc
vscode_essentials/vsix/.gitkeep
vscode_essentials/vsix/Continue.continue-1.1.66@linux-x64.vsix
vscode_essentials/vsix/ms-python.python-2025.4.0.vsix
vscode_essentials-0.3.0.dist-info/licenses/LICENSE
vscode_essentials-0.3.0.dist-info/METADATA
vscode_essentials-0.3.0.dist-info/WHEEL
vscode_essentials-0.3.0.dist-info/top_level.txt
vscode_essentials-0.3.0.dist-info/RECORD
