Metadata-Version: 2.4
Name: vscode-essentials
Version: 0.3.0
Summary: Essential utilities for VS Code development
Author-email: SAI <me@steveimm.id>
License: MIT
Project-URL: Homepage, https://github.com/yourusername/vscode-essentials
Project-URL: Repository, https://github.com/yourusername/vscode-essentials
Project-URL: Issues, https://github.com/yourusername/vscode-essentials/issues
Keywords: vscode,development,utilities
Classifier: Development Status :: 3 - Alpha
Classifier: Intended Audience :: Developers
Classifier: License :: OSI Approved :: MIT License
Classifier: Programming Language :: Python :: 3
Classifier: Programming Language :: Python :: 3.8
Classifier: Programming Language :: Python :: 3.9
Classifier: Programming Language :: Python :: 3.10
Classifier: Programming Language :: Python :: 3.11
Classifier: Programming Language :: Python :: 3.12
Requires-Python: >=3.8
License-File: LICENSE
Dynamic: license-file
